hipr/__init__.py
hipr/constraints.py
hipr/extraction.py
hipr/generation.py
hipr/models.py
hipr/py.typed
hipr/typedefs.py
hipr/cli/__init__.py
hipr/cli/generate_stubs.py
hipr/stubs/__init__.py
hipr/stubs/generator.py
hipr/stubs/scanner.py
hipr-0.1.13.dist-info/licenses/LICENSE
hipr-0.1.13.dist-info/METADATA
hipr-0.1.13.dist-info/WHEEL
hipr-0.1.13.dist-info/entry_points.txt
hipr-0.1.13.dist-info/top_level.txt
hipr-0.1.13.dist-info/RECORD
