Metadata-Version: 2.4
Name: hipr
Version: 0.1.13
Summary: Automatic Pydantic config generation from function signatures with hyperparameters
Author-email: "Sencer S." <nospam@gmail.com>
License: MIT
Requires-Python: >=3.12
License-File: LICENSE
Requires-Dist: pydantic>=2.0.0
Requires-Dist: annotated-types>=0.6.0
Provides-Extra: dev
Requires-Dist: basedpyright>=1.31.7; extra == "dev"
Requires-Dist: ruff>=0.1.0; extra == "dev"
Requires-Dist: pytest>=7.0.0; extra == "dev"
Requires-Dist: pytest-cov>=4.0.0; extra == "dev"
Requires-Dist: numpy>=2.3.5; extra == "dev"
Requires-Dist: pandas>=2.3.3; extra == "dev"
Requires-Dist: pandas-stubs>=2.0.0; extra == "dev"
Dynamic: license-file
